ellipse_rcnn/__init__.py
ellipse_rcnn/py.typed
ellipse_rcnn/core/__init__.py
ellipse_rcnn/core/encoder.py
ellipse_rcnn/core/kld.py
ellipse_rcnn/core/model.py
ellipse_rcnn/core/ops.py
ellipse_rcnn/core/roi_head.py
ellipse_rcnn/core/transform.py
ellipse_rcnn/core/types.py
ellipse_rcnn/core/wd.py
ellipse_rcnn/data/__init__.py
ellipse_rcnn/data/base.py
ellipse_rcnn/data/craters.py
ellipse_rcnn/data/fddb.py
ellipse_rcnn/data/utils.py
ellipse_rcnn/hf/__init__.py
ellipse_rcnn/hf/model.py
ellipse_rcnn/pl/__init__.py
ellipse_rcnn/pl/model.py
ellipse_rcnn/utils/__init__.py
ellipse_rcnn/utils/mat.py
ellipse_rcnn/utils/viz.py
ellipse_rcnn-0.2.2.dist-info/METADATA
ellipse_rcnn-0.2.2.dist-info/WHEEL
ellipse_rcnn-0.2.2.dist-info/licenses/LICENSE
ellipse_rcnn-0.2.2.dist-info/RECORD
