Metadata-Version: 2.4
Name: ellipse-rcnn
Version: 0.2.2
Summary: An implementation of the Ellipse R-CNN object detection model in PyTorch, based on 'Ellipse R-CNN: Learning to Infer Elliptical Object from Clustering and Occlusion' by Dong et al.
Author-email: Wouter Doppenberg <wouterdoppenberg@gmail.com>
License: MIT
License-File: LICENSE
Keywords: PyTorch,computer vision,deep learning,ellipse,rcnn
Requires-Python: >=3.12
Requires-Dist: torch>=2.5.1
Requires-Dist: torchvision>=0.20.1
Provides-Extra: hf
Requires-Dist: huggingface-hub>=0.27.1; extra == 'hf'
Requires-Dist: safetensors>=0.5.2; extra == 'hf'
Provides-Extra: train
Requires-Dist: h5py>=3.12.1; extra == 'train'
Requires-Dist: matplotlib>=3.10.0; extra == 'train'
Requires-Dist: pandas>=2.2.3; extra == 'train'
Requires-Dist: pytorch-lightning>=2.5.0.post0; extra == 'train'
Requires-Dist: seaborn>=0.13.2; extra == 'train'
Requires-Dist: tensorboard>=2.18.0; extra == 'train'
Requires-Dist: torch-tb-profiler>=0.4.3; extra == 'train'
Requires-Dist: torchmetrics>=1.6.1; extra == 'train'
Requires-Dist: typer>=0.15.1; extra == 'train'
